pyluwen-0.8.1.dist-info/METADATA
pyluwen-0.8.1.dist-info/WHEEL
pyluwen/__init__.py
pyluwen/__init__.pyi
pyluwen/py.typed
pyluwen/pyluwen.cpython-39-x86_64-linux-gnu.so
pyluwen-0.8.1.dist-info/RECORD
