Metadata-Version: 2.4
Name: pyluwen
Version: 0.8.1
Classifier: Programming Language :: Rust
Classifier: Programming Language :: Python :: Implementation :: CPython
Classifier: Programming Language :: Python :: Implementation :: PyPy
Classifier: License :: OSI Approved :: Apache Software License
Classifier: Operating System :: POSIX :: Linux
Classifier: Topic :: System :: Hardware
Classifier: Topic :: Utilities
Summary: Python bindings for luwen
Keywords: Tenstorrent,Wormhole,Blackhole
Author: Daniel Rosen <drosen@tenstorrent.com>
Author-email: Daniel Rosen <drosen@tenstorrent.com>
License: Apache-2.0
Requires-Python: >=3.10
Project-URL: Source Code, https://github.com/tenstorrent/luwen
